<firmware>
    <mirrors allow_custom="true">
        <mirror>
            <url/>
            <description>(default)</description>
        </mirror>
        <mirror>
            <url>http://packages.dynfi.com</url>
            <description>DynFi (France)</description>
        </mirror>
    </mirrors>
    <flavours>
        <flavour>
            <name/>
            <description>(default)</description>
        </flavour>
    </flavours>
    <families>
        <family>
            <name/>
            <description>Production</description>
        </family>
        <family>
            <name>devel</name>
            <description>Development</description>
        </family>
    </families>
</firmware>
